urmom/__init__.py
urmom/ascii_art.py
urmom-0.1.1.dist-info/LICENSE
urmom-0.1.1.dist-info/METADATA
urmom-0.1.1.dist-info/WHEEL
urmom-0.1.1.dist-info/entry_points.txt
urmom-0.1.1.dist-info/top_level.txt
urmom-0.1.1.dist-info/RECORD
