Metadata-Version: 2.1
Name: urmom
Version: 0.1.1
Summary: A Python package that prints 'URMOM' in ASCII art.
Home-page: https://github.com/danielmerja/urmom
Author: Daniel Merja
Author-email: danielmerja@gmail.com
Classifier: Programming Language :: Python :: 3
Classifier: License :: OSI Approved :: MIT License
Classifier: Operating System :: OS Independent
Requires-Python: >=3.6
License-File: LICENSE
